<edmx:Edmx xmlns:edmx="http://docs.oasis-open.org/odata/ns/edmx" Version="4.0">
<edmx:Reference Uri="https://sap.github.io/odata-vocabularies/vocabularies/Common.xml">
<edmx:Include Alias="Common" Namespace="com.sap.vocabularies.Common.v1"/>
</edmx:Reference>
<edmx:Reference Uri="https://oasis-tcs.github.io/odata-vocabularies/vocabularies/Org.OData.Core.V1.xml">
<edmx:Include Alias="Core" Namespace="Org.OData.Core.V1"/>
</edmx:Reference>
<edmx:DataServices>
<Schema xmlns="http://docs.oasis-open.org/odata/ns/edm" Namespace="hanaservice">
<EntityContainer Name="EntityContainer">
<EntitySet Name="customer" EntityType="hanaservice.customer">
<NavigationPropertyBinding Path="address" Target="Address"/>
</EntitySet>
<EntitySet Name="Address" EntityType="hanaservice.Address">
<NavigationPropertyBinding Path="customer" Target="customer"/>
</EntitySet>
</EntityContainer>
<EntityType Name="customer">
<Key>
<PropertyRef Name="customerId"/>
</Key>
<Property Name="customerId" Type="Edm.String" Nullable="false"/>
<Property Name="customerFirstName" Type="Edm.String"/>
<Property Name="customerLastName" Type="Edm.String"/>
<NavigationProperty Name="address" Type="Collection(hanaservice.Address)" Partner="customer"/>
</EntityType>
<EntityType Name="Address">
<Key>
<PropertyRef Name="adressId"/>
</Key>
<Property Name="adressId" Type="Edm.String" Nullable="false"/>
<Property Name="addressLine1" Type="Edm.String"/>
<Property Name="addressLine2" Type="Edm.String"/>
<Property Name="addressLine3" Type="Edm.String"/>
<NavigationProperty Name="customer" Type="hanaservice.customer" Partner="address">
<ReferentialConstraint Property="customer_customerId" ReferencedProperty="customerId"/>
</NavigationProperty>
<Property Name="customer_customerId" Type="Edm.String"/>
</EntityType>
</Schema>
</edmx:DataServices>
</edmx:Edmx>